{"https://github.com": {"timestamp": 1761484461.0288658, "data": {"report": "🔗 *Проверка ссылки:* https://github.com\n\n🧭 Google Safe Browsing: clean\n🧪 VirusTotal: clean\n🚨 Blacklists: clean\n\n⚠️ *Уровень риска:* НИЗКИЙ (0 баллов)\n\n🌐 *Инфраструктура сайта:*\n🏠 Домен: `github.com`\n🔒 HTTPS: Да\n📜 Сертификат выдан: *Sectigo Limited*\n📅 Действителен до: `2026-02-05 23:59:59`\n🕐 Осталось дней: `102`\n\n🌍 *Хостинг:*\n🧩 IP: `140.82.121.4`\n🏳️ Страна: Germany\n🏢 Организация: GITHUB\n🛰 ASN: AS36459\n📦 CDN: Не используется или неизвестен\n\n✅ Признаков прокси или подозрительного хостинга не найдено\n📖 *Данные о домене:*\n🗓 Дата регистрации: Unknown\n🏢 Регистратор: Unknown\n📆 Возраст домена: N/A дней (~0 лет)\n🕐 Срок действия до: Unknown\n🧭 Риск: N/A (риск: N/A)\n", "results": {"google": {"status": "clean", "details": null}, "vt": {"status": "clean", "details": {"malicious": 0, "suspicious": 0, "undetected": 26, "harmless": 72, "timeout": 0}}, "blacklist": {"status": "clean", "details": null}, "infra": {"hostname": "github.com", "is_https": true, "ssl_info": {"valid": true, "issued_to": "github.com", "issued_by": "Sectigo Limited", "valid_from": "2025-02-05 00:00:00", "valid_to": "2026-02-05 23:59:59", "days_left": 102}, "ip_info": {"ip": "140.82.121.4", "country": "Germany", "org": "GITHUB", "asn": "AS36459"}, "cdn": "Не используется или неизвестен", "proxy_suspect": false, "whois": {"error": "WHOIS error: can't subtract offset-naive and offset-aware datetimes"}}}}}}